etherswarm/__init__.py
etherswarm/__main__.py
etherswarm/accounts.py
etherswarm/cmd.py
etherswarm/contract.py
etherswarm/ethereum.py
etherswarm/gasprice.py
etherswarm/provider.py
etherswarm/utils.py
EtherSwarm-0.1.dist-info/METADATA
EtherSwarm-0.1.dist-info/WHEEL
EtherSwarm-0.1.dist-info/entry_points.txt
EtherSwarm-0.1.dist-info/top_level.txt
EtherSwarm-0.1.dist-info/RECORD
